helper_streamlit_utils/__init__.py
helper_streamlit_utils/helper_streamlit_utils.py
helper_streamlit_utils-0.1.0.dist-info/licenses/LICENSE
helper_streamlit_utils-0.1.0.dist-info/METADATA
helper_streamlit_utils-0.1.0.dist-info/WHEEL
helper_streamlit_utils-0.1.0.dist-info/top_level.txt
helper_streamlit_utils-0.1.0.dist-info/RECORD
