Metadata-Version: 2.4
Name: helper-streamlit-utils
Version: 0.1.0
Summary: Streamlit 유틸리티 모음 라이브러리: 스타일링, 레이아웃, 커스텀 컴포넌트
Author-email: c0z0c <c0z0c.dev@gmail.com>
License: MIT
Project-URL: Homepage, https://github.com/c0z0c-helper/helper_streamlit_utils
Project-URL: Repository, https://github.com/c0z0c-helper/helper_streamlit_utils
Project-URL: Issues, https://github.com/c0z0c-helper/helper_streamlit_utils/issues
Keywords: streamlit,utilities,styling,layout,components,ui,web,dashboard,visualization
Classifier: Development Status :: 4 - Beta
Classifier: Intended Audience :: Developers
Classifier: Intended Audience :: Science/Research
Classifier: Programming Language :: Python :: 3
Classifier: Programming Language :: Python :: 3.8
Classifier: Programming Language :: Python :: 3.9
Classifier: Programming Language :: Python :: 3.10
Classifier: Programming Language :: Python :: 3.11
Classifier: Programming Language :: Python :: 3.12
Classifier: Programming Language :: Python :: 3.13
Classifier: Topic :: Software Development :: Libraries :: Python Modules
Classifier: Topic :: Utilities
Requires-Python: >=3.8
License-File: LICENSE
Requires-Dist: streamlit>=1.20.0
Requires-Dist: helper-dev-utils>=0.5.0
Provides-Extra: dev
Requires-Dist: pytest>=7.0.0; extra == "dev"
Requires-Dist: pytest-cov>=4.0.0; extra == "dev"
Requires-Dist: black>=23.0.0; extra == "dev"
Requires-Dist: ruff>=0.1.0; extra == "dev"
Provides-Extra: all
Dynamic: license-file
